Workbook

Sheet INICIO
C2: SUSAN DANIELA RIVERA TORREALBA
C3: C.C. 1.140.418.986

Sheet EGRESOS 
C2: SUSAN DANIELA RIVERA TORREALBA
C3: C.C. 1.140.418.986
C4: CONTROL DE EGRESOS
C8: DIA | D8: TERCERO | E8: DESCRIPCION | F8: COSTOS | G8: G. PERSONAL | H8: G. SERVICIOS | I8: OTROS GASTOS | J8: DEPOSITOS | K8: TOTAL DIA | L8: TOTAL MES
C9: 1 | D9: FRUTAS EL PAISA | E9: COMPRA DE INSUMOS | F9: 40000 | G9: 0 | H9: 0 | I9: 0 | K9: 0 | P9: NIT ó CC | Q9: Columna1
D10: HIELO LA ROCA | E10: COMPRA DE INSUMOS | F10: 10000 | G10: 0 | H10: 0 | I10: 0 | K10: 0 | Q10: TERCEROS
D11: BIMBO | E11: COMPRA DE INSUMOS | F11: 25852 | G11: 0 | H11: 0 | I11: 0 | K11: 0 | Q11: (OSO) DISTRIBUCIONES 2A SAS
D12: CHALOS | E12: COMPRA DE INSUMOS | F12: 145100 | G12: 0 | H12: 0 | I12: 0 | K12: 0 | Q12: AGUA ESSENCIA
D13: THAIS MERCADO | E13: PAGO TURNO MAÑANA | F13: 0 | G13: 65000 | H13: 0 | I13: 0 | K13: 0 | Q13: AIR-E
D14: ARA | E14: COMPRA DE INSUMOS | F14: 34450 | G14: 0 | H14: 0 | I14: 0 | K14: 0 | Q14: ALMACEN ELECTROSAN
D15: ALMACENES D1 | E15: COMPRA DE INSUMOS | F15: 22850 | G15: 0 | H15: 0 | I15: 0 | K15: 0 | Q15: ALMACENES D1
D16: OLIMPICA | E16: COMPRA DE INSUMOS | F16: 38050 | G16: 0 | H16: 0 | I16: 0 | K16: 0 | Q16: APORTES EN LINEA
D17: ERNESTO OCHOA | E17: DOMICILIO CLIENTE | F17: 0 | G17: 0 | H17: 0 | I17: 5000 | K17: 0 | Q17: ARA
D18: ARA | E18: COMPRA DE INSUMOS | F18: 8990 | G18: 0 | H18: 0 | I18: 0 | K18: 0 | Q18: BIMBO
D19: ERNESTO OCHOA | E19: DOMICILIO CLIENTE | F19: 0 | G19: 0 | H19: 0 | I19: 5000 | K19: 0 | Q19: CACHARRERIA CLAUDIA
D20: FRUTAS EL PAISA | E20: COMPRA DE INSUMOS | F20: 76900 | G20: 0 | H20: 0 | I20: 0 | K20: 0 | Q20: CHALOS
D21: KARINA PEREZ | E21: PAGO TURNO TARDE | F21: 0 | G21: 55000 | H21: 0 | I21: 0 | K21: 0 | Q21: CLARO
D22: ANA CERVANTES | E22: PAGO TURNO TARDE | F22: 0 | G22: 55000 | H22: 0 | I22: 0 | K22: 0 | Q22: COCA COLA
F23: 0 | G23: 0 | H23: 0 | I23: 0 | K23: 0 | L23: =SUM(F9:F12)+G13 -> 285952 | Q23: COLOMBINA
F24: 0 | G24: 0 | H24: 0 | I24: 0 | K24: 0 | L24: =SUM(F14+F15+F16+I17+F18+I19+F20) -> 191240 | Q24: COMERCIALIZADORA BIOSTIVEN
E25: TOTALES | F25: =SUM(F9:F24) -> 402192 | G25: =SUM(G9:G24) -> 175000 | H25: =SUM(H9:H24) -> 0 | I25: =SUM(I9:I24) -> 10000 | J25: =SUM(J9:J24) -> 0 | K25: =SUM(F25:J25)-J25 -> 587192 | Q25: CONSTRUMATERIALES LA FORTUNA
C26: 2 | D26: ANA CERVANTES | E26: PAGO TURNO MAÑANA | F26: 0 | G26: 75000 | H26: 0 | I26: 0 | K26: 0 | Q26: D1
D27: OLIMPICA | E27: COMPRA DE INSUMOS | F27: 15320 | G27: 0 | H27: 0 | I27: 0 | K27: 0 | Q27: DISTRIBUIDORA BUCARAMANGA
D28: ARA | E28: COMPRA DE INSUMOS | F28: 33200 | G28: 0 | H28: 0 | I28: 0 | K28: 0 | Q28: DISTRIBUIDORA DON TOMATO
D29: ALMACENES D1 | E29: COMPRA DE INSUMOS | F29: 10850 | G29: 0 | H29: 0 | I29: 0 | K29: 0 | Q29: DISTRIPLASTICO LUCY
D30: MAKRO | E30: COMPRA DE INSUMOS | F30: 199850 | G30: 0 | H30: 0 | I30: 0 | K30: 0 | Q30: DÓLAR CITY
D31: ARA | E31: COMPRA DE INSUMOS | F31: 14370 | G31: 0 | H31: 0 | I31: 0 | K31: 0 | Q31: DOMICILIO
D32: KARINA PEREZ | E32: PAGO TURNO TARDE | F32: 0 | G32: 75000 | H32: 0 | I32: 0 | K32: 0 | Q32: DONDE LUCY
D33: THAIS MERCADO | E33: PAGO TURNO TARDE | F33: 0 | G33: 75000 | H33: 0 | I33: 0 | K33: 0 | Q33: DOXA
D34: JUAN VILLABONA | E34: MERIENDA | F34: 0 | G34: 8000 | H34: 0 | I34: 0 | K34: 0 | Q34: FRUVER ALVEG SAS
D35: FRUTAS EL PAISA | E35: COMPRA DE INSUMOS | F35: 147200 | G35: 0 | I35: 0 | K35: 0 | Q35: FULL HOGAR
D36: COMISION | E36: COMPRA DE INSUMOS | F36: 0 | G36: 0 | H36: 0 | I36: 10000 | K36: 0 | Q36: GASES DEL CARIBE
D37: DOMICILIO CLIENTE | E37: DOMICILIO CLIENTE | F37: 0 | G37: 0 | H37: 0 | I37: 5000 | K37: 0 | Q37: HELADOS COLOMBIA
D38: CHALOS | E38: COMPRA DE INSUMOS | F38: 153200 | G38: 0 | H38: 0 | I38: 0 | K38: 0 | Q38: HIELO LA ROCA
F39: 0 | G39: 0 | H39: 0 | I39: 0 | K39: 0 | Q39: HOTEL CHAYRAMA
F40: 0 | G40: 0 | H40: 0 | I40: 0 | K40: 0 | Q40: ISMAR TORREALBA
F41: 0 | G41: 0 | H41: 0 | I41: 0 | K41: 0 | L41: =SUM(G26) -> 75000 | Q41: JAIRO LOPEZ
F42: 0 | G42: 0 | H42: 0 | I42: 0 | K42: 0 | L42: =SUM(F27:F29) -> 59370 | Q42: JOSE RIVERA
E43: TOTALES | F43: =SUM(F26:F42) -> 573990 | G43: =SUM(G26:G42) -> 233000 | H43: =SUM(H26:H42) -> 0 | I43: =SUM(I26:I42) -> 15000 | J43: =SUM(J26:J42) -> 0 | K43: =SUM(F43:J43)-J43 -> 821990 | L43: =L41+L42 -> 134370 | Q43: JULIAN RIVERA
C44: 3 | D44: OLIMPICA | E44: COMPRA DE INSUMOS | F44: 35280 | G44: 0 | H44: 0 | I44: 0 | K44: 0 | Q44: KARINA PEREZ
D45: OLIMPICA | E45: COMPRA DE INSUMOS | F45: 4700 | G45: 0 | H45: 0 | I45: 0 | K45: 0 | Q45: LA ESTRELLA DE SANTA MARTA
D46: HIELO LA ROCA | E46: COMPRA DE INSUMOS | F46: 20000 | G46: 0 | H46: 0 | I46: 0 | K46: 0 | Q46: LICORERA BRISAS
D47: HOME CENTER | E47: COMPRA DE LAMPARA | F47: 0 | G47: 0 | H47: 0 | I47: 19900 | K47: 0 | Q47: LICORERIA BRISAS
D48: (OSO) DISTRIBUCIONES 2A SAS | E48: COMPRA DE INSUMOS | F48: 51000 | G48: 0 | H48: 0 | I48: 0 | K48: 0 | Q48: LUIS ROMERO
D49: OLIMPICA | E49: COMPRA DE INSUMOS | F49: 2410 | G49: 0 | H49: 0 | I49: 0 | K49: 0 | Q49: MAKRO
D50: ALMACENES D1 | E50: COMPRA DE INSUMOS | F50: 16890 | G50: 0 | H50: 0 | I50: 0 | K50: 0 | Q50: CLICK PUBLICIDAD
D51: ARA | E51: COMPRA DE INSUMOS | F51: 47690 | G51: 0 | H51: 0 | I51: 0 | K51: 0 | Q51: MEGA FRUVER RODADERO
D52: TERESITA MEDRANO | E52: PAGO TURNO MAÑANA | F52: 0 | G52: 65000 | H52: 0 | I52: 0 | K52: 0 | Q52: MERKAFRUVER
D53: KARINA PEREZ | E53: PAGO TURNO MAÑANA | F53: 0 | G53: 65000 | H53: 0 | I53: 0 | K53: 0 | Q53: MERKAFRUVER RODADERO
D54: TRES OSITOS | E54: COMPRA DE LAPICEROS | F54: 0 | G54: 0 | H54: 0 | I54: 3000 | K54: 0 | Q54: GLADIS PEREZ
D55: MERCADO CAMPESINO LA CENTRAL | E55: COMPRA DE INSUMOS | F55: 20000 | G55: 0 | H55: 0 | I55: 0 | K55: 0 | Q55: MULTIMARCAS DEL CARIBE
D56: MERCADO CAMPESINO LA CENTRAL | E56: COMPRA DE INSUMOS | F56: 27000 | G56: 0 | H56: 0 | I56: 0 | K56: 0 | Q56: OLIMPICA
D57: FRUTAS EL PAISA | E57: COMPRA DE INSUMOS | F57: 157600 | G57: 0 | H57: 0 | I57: 0 | K57: 0 | L57: =SUM(F44)+F45+F46+F48+F49+F50+F51+G52+G53+I54 -> 310970 | Q57: PAPELERIA ARCHILA
D58: WILLIAM MENDEZ | E58: DOMICILIO CLIENTE | F58: 0 | G58: 0 | H58: 0 | I58: 5000 | K58: 0 | L58: =SUM(F55+F56+F57+I58+G59+G60) -> 339600 | Q58: PAPELERIA PLAYANET
D59: THAIS MERCADO | E59: PAGO TURNO TARDE | F59: 0 | G59: 65000 | H59: 0 | I59: 0 | K59: 0 | Q59: CEL 72
D60: ANA CERVANTES | E60: PAGO TURNO TARDE | F60: 0 | G60: 65000 | H60: 0 | I60: 0 | K60: 0 | Q60: PELLO SOPAS
E61: TOTALES | F61: =SUM(F44:F60) -> 382570 | G61: =SUM(G44:G60) -> 260000 | H61: =SUM(H44:H60) -> 0 | I61: =SUM(I44:I60) -> 27900 | J61: =SUM(J44:J60) -> 0 | K61: =SUM(F61:J61)-J61 -> 670470 | Q61: RAPIMERCAR
C62: 4 | D62: HOTEL CHAYRAMA | E62: PAGO ARIRIENDO | F62: 0 | G62: 0 | H62: 2127000 | I62: 0 | K62: 0 | Q62: SAHARA
D63: GASES DEL CARIBE | E63: PAGO SERVICIO DE GAS | F63: 0 | H63: 12097 | I63: 0 | K63: 0 | Q63: SEBASTIAN VILLABONA
D64: APORTES EN LINEA | E64: PAGO APORTES EN LINEA SUSAN RIVERA | F64: 0 | G64: 0 | H64: 0 | I64: 405800 | K64: 0 | Q64: SUSAN RIVERA
D65: H2O BRISAS DE MANGLARES | E65: COMPRA DE INSUMOS | F65: 15000 | G65: 0 | H65: 0 | I65: 0 | K65: 0 | Q65: THAIS MERCADO
D66: ANA CERVANTES | E66: PAGO TURNO MAÑANA | F66: 0 | G66: 50000 | H66: 0 | I66: 0 | K66: 0 | Q66: HOGAR KING
D67: MAKRO | E67: COMPRA DE INSUMOS | F67: 239900 | G67: 0 | H67: 0 | I67: 0 | K67: 0 | Q67: SURTIMERCAR LA 13
D68: JUAN VILLABONA | E68: DOMICILIO CLIENTE | F68: 0 | G68: 0 | H68: 0 | I68: 10000 | K68: 0 | Q68: BIO-STIVEN
D69: KARINA PEREZ | E69: BONO EMPLEADO | F69: 0 | G69: 18000 | H69: 0 | I69: 0 | K69: 0 | Q69: WILLIAM MENDEZ
D70: THAIS MERCADO | E70: BONO EMPLEADO | F70: 0 | G70: 18000 | H70: 0 | I70: 0 | K70: 0 | Q70: YERSON MOLINA
D71: FRUTAS EL PAISA | E71: COMPRA DE INSUMOS | F71: 96400 | G71: 0 | H71: 0 | I71: 0 | K71: 0 | Q71: YESID ALFONZO
D72: OLIMPICA | E72: COMPRA DE INSUMOS | F72: 19360 | G72: 0 | H72: 0 | I72: 0 | K72: 0 | Q72: MERCADO CAMPESINO LA CENTRAL
D73: CHALOS | E73: COMPRA DE INSUMOS | F73: 170700 | G73: 0 | H73: 0 | I73: 0 | K73: 0 | Q73: VARIEDADES LA 10 - GAIRA
D74: ARA | E74: COMPRA DE INSUMOS | F74: 10850
D75: ALMACENES D1 | E75: COMPRA DE INSUMOS | F75: 61550 | L75: =SUM(H63)+F65+G66 -> 77097
D76: WILLIAM MENDEZ | E76: DOMICILIO CLIENTE | F76: 0 | G76: 0 | H76: 0 | I76: 5000 | K76: 0 | L76: =SUM(F71:F75)+F67+I68 -> 608760 | Q76: WILLIAM MENDEZ
D77: TERESITA MEDRANO | E77: PAGO TURNO TARDE | G77: 50000 | L77: =L75+L76 -> 685857
D78: THAIS MERCADO | E78: PAGO TURNO TARDE | F78: 0 | G78: 50000 | H78: 0 | I78: 0 | K78: 0 | Q78: EL CENTRO DEL CACHARRO
E79: TOTALES | F79: =SUM(F62:F78) -> 613760 | G79: =SUM(G62:G78) -> 186000 | H79: =SUM(H62:H78) -> 2139097 | I79: =SUM(I62:I78) -> 420800 | J79: =SUM(J62:J78) -> 0 | K79: =SUM(F79:J79)-J79 -> 3359657 | Q79: CABANA
C80: 5 | D80: TERESITA MEDRANO | E80: PAGO TURNO MAÑANA | G80: 50000 | H80: 0 | I80: 0 | K80: 0 | Q80: CAMILO GALVIS
D81: COLOMBINA | E81: COMPRA DE INSUMOS | F81: 144161 | G81: 0 | H81: 0 | I81: 0 | K81: 0 | Q81: JAINER LOPEZ
D82: BIMBO | E82: COMPRA DE INSUMOS | F82: 25852 | G82: 0 | H82: 0 | I82: 0 | K82: 0 | Q82: IVAN CERVANTES
D83: OLIMPICA | E83: COMPRA DE INSUMOS | F83: 22090 | G83: 0 | H83: 0 | I83: 0 | K83: 0 | Q83: VERDURAS EL PAISA
D84: COCA COLA | E84: COMPRA DE INSUMOS | F84: 90550 | H84: 0 | I84: 0 | K84: 0 | Q84: DISTRIBUIDORA SENSACION
D85: FRUTAS EL PAISA | E85: COMPRA DE INSUMOS | F85: 65800 | G85: 0 | H85: 0 | I85: 0 | K85: 0 | Q85: MERCADO CAMPESINO LA CENTRAL
D86: KARINA PEREZ | E86: PAGO TURNO TARDE | F86: 0 | G86: 50000 | H86: 0 | I86: 0 | K86: 0 | Q86: SURTIMERCAR LA 13
D87: THAIS MERCADO | E87: PAGO TURNO TARDE | F87: 0 | G87: 50000 | H87: 0 | I87: 0 | K87: 0 | Q87: REFRIELECTRI
D88: TERESITA MEDRANO | E88: BONO EMPLEADO | F88: 0 | G88: 5000 | H88: 0 | I88: 0 | K88: 0 | Q88: REAL BLENDS
F89: 0 | G89: 0 | H89: 0 | I89: 0 | K89: 0 | Q89: LUNA AZUL
F90: 0 | G90: 0 | H90: 0 | I90: 0 | K90: 0 | Q90: JESUS ESCOBAR
F91: 0 | G91: 0 | H91: 0 | I91: 0 | K91: 0 | Q91: PAGO SERVICIO AGUA
F92: 0 | G92: 0 | H92: 0 | I92: 0 | K92: 0 | Q92: FABIO TARAZONA
F93: 0 | G93: 0 | H93: 0 | I93: 0 | K93: 0 | Q93: FRUTAS
F94: 0 | G94: 0 | H94: 0 | I94: 0 | K94: 0 | Q94: H2O BRISAS DE MANGLARES
F95: 0 | G95: 0 | H95: 0 | I95: 0 | K95: 0 | L95: =SUM(G80+F81+F82) -> 220013 | Q95: COMERCIALIZADORA BIOSTIVEN
F96: 0 | G96: 0 | H96: 0 | I96: 0 | K96: 0 | L96: =SUM(F85) -> 65800 | Q96: SEBASTIAN VILLABONA
E97: TOTALES | F97: =SUM(F80:F96) -> 348453 | G97: =SUM(G81:G96) -> 105000 | H97: =SUM(H80:H96) -> 0 | I97: =SUM(I80:I96) -> 0 | J97: =SUM(J80:J96) -> 0 | K97: =SUM(F97:J97)-J97 -> 453453 | L97: =L95+L96 -> 285813 | Q97: HOGAR KING
C98: 6 | D98: FRUTAS EL PAISA | E98: COMPRA DE INSUMOS | F98: 72100 | G98: 0 | H98: 0 | I98: 0 | K98: 0 | Q98: FRUTAS EL PAISA
D99: HIELO LA ROCA | E99: COMPRA DE INSUMOS | F99: 10000 | G99: 0 | H99: 0 | I99: 0 | K99: 0 | Q99: FABIANA
D100: ANA CERVANTES | E100: PAGO TURNO MAÑANA | F100: 0 | G100: 55000 | H100: 0 | I100: 0 | K100: 0 | Q100: TERESITA MEDRANO
D101: ALMACENES D1 | E101: COMPRA DE INSUMOS | F101: 13850 | G101: 0 | H101: 0 | I101: 0 | K101: 0
D102: ARA | E102: COMPRA DE INSUMOS | F102: 16238 | G102: 0 | H102: 0 | I102: 0 | K102: 0
D103: OLIMPICA | E103: COMPRA DE INSUMOS | F103: 22090 | G103: 0 | H103: 0 | I103: 0 | K103: 0 | Q103: SURTIMERCAR LA 13
D104: THAIS MERCADO | E104: BONO EMPLEADO | F104: 0 | G104: 9000 | H104: 0 | I104: 0 | K104: 0 | Q104: BIO-STIVEN
...

Sheet VENTAS
C3: SUSAN DANIELA RIVERA TORREALBA
C4: C.C.1.140.418.986
C5: VENTAS
G7: =+'EGRESOS '!G7 -> 0
C9: DIA | D9: FORMA | E9: MONTO | F9: INGRE AUT | G9: EGRESO | H9: SALDO | I9: NOVEDAD
C10: 1 | D10: EFECTIVO | E10: =441000+383000 -> 824000
C11: 1 | D11: TARJETA | E11: =35000+303000 -> 338000
C12: TOTAL | E12: =SUM(E10:E11) -> 1162000 | F12: =SUM(F10:F11) -> 0 | G12: =+'EGRESOS '!K25 -> 587192 | H12: =+E12-G12 -> 574808
C13: 2 | D13: EFECTIVO | E13: 1219000
C14: 2 | D14: TARJETA | E14: 586000
C15: TOTAL | E15: =SUM(E13:E14) -> 1805000 | F15: =SUM(F13:F14) -> 0 | G15: =+'EGRESOS '!K43 -> 821990 | H15: =+H12+E15-G15 -> 1557818
C16: 3 | D16: EFECTIVO | E16: =363000+404000 -> 767000
C17: 3 | D17: TARJETA | E17: =77000+233000 -> 310000
C18: TOTAL | E18: =SUM(E16:E17) -> 1077000 | F18: =SUM(F16:F17) -> 0 | G18: =+'EGRESOS '!K61 -> 670470 | H18: =+H15+E18-G18 -> 1964348
C19: 4 | D19: EFECTIVO | E19: =161000+288000 -> 449000 | I19: BONO EMPLEADO KARINA PEREZ 18.000 Y THAIS MERCADO 18.000
C20: 4 | D20: TARJETA | E20: =7000+192000 -> 199000
C21: TOTAL | E21: =SUM(E19:E20) -> 648000 | F21: =SUM(F19:F20) -> 0 | G21: =+'EGRESOS '!K79 -> 3359657 | H21: =+H18+E21-G21 -> -747309
C22: 5 | D22: EFECTIVO | E22: =35000+253000 -> 288000 | I22: BONO EMPLEADO 5000
C23: 5 | D23: TARJETA | E23: =30000+104000 -> 134000
C24: TOTAL | E24: =SUM(E22:E23) -> 422000 | F24: =SUM(F22:F23) -> 0 | G24: =+'EGRESOS '!K97 -> 453453 | H24: =+H21+E24-G24 -> -778762
C25: 6 | D25: EFECTIVO | E25: =168000+245000 -> 413000 | I25: BONO EMPLEADO THAIS MERCADO $9.000 Y KARINA PEREZ $5.000
C26: 6 | D26: TARJETA | E26: =65000+133000 -> 198000
C27: TOTAL | E27: =SUM(E25:E26) -> 611000 | F27: =SUM(F25:F26) -> 0 | G27: =+'EGRESOS '!K115 -> 385678 | H27: =+H24+E27-G27 -> -553440
C28: 7 | D28: EFECTIVO | E28: =142500+363000 -> 505500
C29: 7 | D29: TARJETA | E29: =61000+94000 -> 155000
C30: TOTAL | E30: =SUM(E28:E29) -> 660500 | F30: =SUM(F28:F29) -> 0 | G30: =+'EGRESOS '!K132 -> 264151 | H30: =+H27+E30-G30 -> -157091
C31: 8 | D31: EFECTIVO | E31: 800000
C32: 8 | D32: TARJETA | E32: 253000
C33: TOTAL | E33: =SUM(E31:E32) -> 1053000 | F33: =SUM(F31:F32) -> 0 | G33: =+'EGRESOS '!K150 -> 673560 | H33: =+H30+E33-G33 -> 222349
C34: 9 | D34: EFECTIVO | E34: =214000+556000 -> 770000
C35: 9 | D35: TARJETA | E35: =64000+145000 -> 209000
C36: TOTAL | E36: =SUM(E34:E35) -> 979000 | F36: =SUM(F34:F35) -> 0 | G36: =+'EGRESOS '!K169 -> 432180 | H36: =+H33+E36-G36 -> 769169
C37: 10 | D37: EFECTIVO | E37: =173000+418000 -> 591000
C38: 10 | D38: TARJETA | E38: =30000+194000 -> 224000
C39: TOTAL | E39: =SUM(E37:E38) -> 815000 | F39: =SUM(F37:F38) -> 0 | G39: =+'EGRESOS '!K186 -> 602870 | H39: =+H36+E39-G39 -> 981299
C40: 11 | D40: EFECTIVO | E40: =213500+397000 -> 610500
C41: 11 | D41: TARJETA | E41: 183000
C42: TOTAL | E42: =SUM(E40:E41) -> 793500 | F42: =SUM(F40:F41) -> 0 | G42: =+'EGRESOS '!K204 -> 852713 | H42: =+H39+E42-G42 -> 922086
C43: 12 | D43: EFECTIVO | E43: =231000+405000 -> 636000
C44: 12 | D44: TARJETA | E44: =48000+275500 -> 323500
C45: TOTAL | E45: =SUM(E43:E44) -> 959500 | F45: =SUM(F43:F44) -> 0 | G45: =+'EGRESOS '!K224 -> 511402 | H45: =+H42+E45-G45 -> 1370184
C46: 13 | D46: EFECTIVO | E46: =237000+414400 -> 651400 | I46: BONO EMPLEADO 4000
C47: 13 | D47: TARJETA | E47: 208000
C48: TOTAL | E48: =SUM(E46:E47) -> 859400 | F48: =SUM(F46:F47) -> 0 | G48: =+'EGRESOS '!K242 -> 310410 | H48: =+H45+E48-G48 -> 1919174
C49: 14 | D49: EFECTIVO | E49: =152000+157000 -> 309000
C50: 14 | D50: TARJETA | E50: =58000+244000 -> 302000
C51: TOTAL | E51: =SUM(E49:E50) -> 611000 | F51: =SUM(F49:F50) -> 0 | G51: =+'EGRESOS '!K261 -> 876008 | H51: =+H48+E51-G51 -> 1654166
C52: 15 | D52: EFECTIVO | E52: =236000+561000 -> 797000
C53: 15 | D53: TARJETA | E53: 173000
C54: TOTAL | E54: =SUM(E52:E53) -> 970000 | F54: =SUM(F52:F53) -> 0 | G54: =+'EGRESOS '!K280 -> 430327 | H54: =+H51+E54-G54 -> 2193839
C55: 16 | D55: EFECTIVO | E55: =59000+820000 -> 879000
C56: 16 | D56: TARJETA | E56: =19000+44000+270000 -> 333000
C57: TOTAL | E57: =SUM(E55:E56) -> 1212000 | F57: =SUM(F55:F56) -> 0 | G57: =+'EGRESOS '!K298 -> 486545 | H57: =+H54+E57-G57 -> 2919294
C58: 17 | D58: EFECTIVO | E58: =519000+330000 -> 849000 | I58: BONO EMPLEADO THAIS MERCADO $2000/ANA CERVANTES $4000
C59: 17 | D59: TARJETA | E59: =124000+94000 -> 218000
C60: TOTAL | E60: =SUM(E58:E59) -> 1067000 | F60: =SUM(F58:F59) -> 0 | G60: =+'EGRESOS '!K317 -> 748651 | H60: =+H57+E60-G60 -> 3237643
C61: 18 | D61: EFECTIVO | E61: =247000+305000 -> 552000 | I61: BONO EMPLEADO TERESITA MEDRANO $5000
C62: 18 | D62: TARJETA | E62: 337000
C63: TOTAL | E63: =SUM(E61:E62) -> 889000 | F63: =SUM(F61:F62) -> 0 | G63: =+'EGRESOS '!K333 -> 603711 | H63: =+H60+E63-G63 -> 3522932
C64: 19 | D64: EFECTIVO | E64: =135000+252500 -> 387500
C65: 19 | D65: TARJETA | E65: =24000+20000 -> 44000
C66: TOTAL | E66: =SUM(E64:E65) -> 431500 | F66: =SUM(F64:F65) -> 0 | G66: =+'EGRESOS '!K351 -> 340613 | H66: =+H63+E66-G66 -> 3613819
C67: 20 | D67: EFECTIVO | E67: =131500+331000 -> 462500
C68: 20 | D68: TARJETA | E68: 491000
C69: TOTAL | E69: =SUM(E67:E68) -> 953500 | F69: =SUM(F67:F68) -> 0 | G69: =+'EGRESOS '!K371 -> 629130 | H69: =+H66+E69-G69 -> 3938189
C70: 21 | D70: EFECTIVO | E70: =199000+492700 -> 691700
C71: 21 | D71: TARJETA | E71: =42000+207500 -> 249500
C72: TOTAL | E72: =SUM(E70:E71) -> 941200 | F72: =SUM(F70:F71) -> 0 | G72: =+'EGRESOS '!K390 -> 569782 | H72: =+H69+E72-G72 -> 4309607
C73: 22 | D73: EFECTIVO | E73: =185500+542000 -> 727500 | I73: BONO EMPLEADO NA CERVANTES $26.000
C74: 22 | D74: TARJETA | E74: 152500
C75: TOTAL | E75: =SUM(E73:E74) -> 880000 | F75: =SUM(F73:F74) -> 0 | G75: =+'EGRESOS '!K409 -> 612317 | H75: =+H72+E75-G75 -> 4577290
C76: 23 | D76: EFECTIVO | E76: =127000+611200 -> 738200
C77: 23 | D77: TARJETA | E77: =100000+301500 -> 401500
C78: TOTAL | E78: =SUM(E76:E77) -> 1139700 | F78: =SUM(F76:F77) -> 0 | G78: =+'EGRESOS '!K425 -> 349926 | H78: =+H75+E78-G78 -> 5367064
C79: 24 | D79: EFECTIVO | E79: =241000+506000 -> 747000
C80: 24 | D80: TARJETA | E80: =85000+139000 -> 224000
C81: TOTAL | E81: =SUM(E79:E80) -> 971000 | F81: =SUM(F79:F80) -> 0 | G81: =+'EGRESOS '!K443 -> 701988 | H81: =+H78+E81-G81 -> 5636076
C82: 25 | D82: EFECTIVO | E82: =171000+455000 -> 626000
C83: 25 | D83: TARJETA | E83: =29000+196000 -> 225000
C84: TOTAL | E84: =SUM(E82:E83) -> 851000 | F84: =SUM(F82:F83) -> 0 | G84: =+'EGRESOS '!K460 -> 592867 | H84: =+H81+E84-G84 -> 5894209
C85: 26 | D85: EFECTIVO | E85: =131500+273000 -> 404500
C86: 26 | D86: TARJETA | E86: =91000+267000 -> 358000
C87: TOTAL | E87: =SUM(E85:E86) -> 762500 | F87: =SUM(F85:F86) -> 0 | G87: =+'EGRESOS '!K477 -> 480775 | H87: =+H84+E87-G87 -> 6175934
C88: 27 | D88: EFECTIVO | E88: =565000+158000 -> 723000
C89: 27 | D89: TARJETA | E89: =160000+205000 -> 365000
C90: TOTAL | E90: =SUM(E88:E89) -> 1088000 | F90: =SUM(F88:F89) -> 0 | G90: =+'EGRESOS '!K494 -> 703737 | H90: =+H87+E90-G90 -> 6560197
C91: 28 | D91: EFECTIVO | E91: =187000+716000 -> 903000
C92: 28 | D92: TARJETA | E92: =86000+260000 -> 346000
C93: TOTAL | E93: =SUM(E91:E92) -> 1249000 | F93: =SUM(F91:F92) -> 0 | G93: =+'EGRESOS '!K511 -> 891326 | H93: =+H90+E93-G93 -> 6917871
C94: 29 | D94: EFECTIVO | E94: =297000+305000 -> 602000
C95: 29 | D95: TARJETA | E95: =141000+161500 -> 302500
C96: TOTAL | E96: =SUM(E94:E95) -> 904500 | F96: =SUM(F94:F95) -> 0 | G96: =+'EGRESOS '!K528 -> 616829 | H96: =+H93+E96-G96 -> 7205542
C97: 30 | D97: EFECTIVO | E97: =258000+414000 -> 672000
C98: 30 | D98: TARJETA | E98: =150500+110000 -> 260500
C99: TOTAL | E99: =SUM(E97:E98) -> 932500 | F99: =SUM(F97:F98) -> 0 | G99: =+'EGRESOS '!K545 -> 320900 | H99: =+H96+E99-G99 -> 7817142
C100: 31 | D100: EFECTIVO
C101: 31 | D101: TARJETA
C102: TOTAL | E102: =SUM(E100:E101) -> 0 | F102: =SUM(F100:F101) -> 0 | G102: =+'EGRESOS '!K562 -> 0 | H102: =+H99+E102-G102 -> 7817142
C103: TOTAL MES | E103: =+E102+E99+E96+E93+E90+E87+E84+E81+E78+E75+E72+E69+E66+E63+E60+E57+E54+E51+E48+E45+E42+E39+E36+E33+E30+E27+E24+E21+E18+E15+E12 -> 27698300 | F103: =+F102+F99+F96+F93+F90+F87+F84+F81+F78+F75+F72+F69+F66+F63+F60+F57+F54+F51+F48+F45+F42+F39+F36+F33+F30+F27+F24+F21+F18+F15+F12 -> 0 | G103: =+G102+G99+G96+G93+G90+G87+G84+G81+G78+G75+G72+G69+G66+G63+G60+G57+G54+G51+G48+G45+G42+G39+G36+G33+G30+G27+G24+G21+G18+G15+G12 -> 19881158 | H103: =+E103-G103 -> 7817142

Sheet RESUMEN MES
C2: =+'EGRESOS '!G7 -> 0
C3: VENTAS
C4: EFECTIVO | D4: =+VENTAS!$E$10+VENTAS!$E$13+VENTAS!$E$16+VENTAS!$E$19+VENTAS!$E$22+VENTAS!$E$25+VENTAS!$E$28+VENTAS!$E$31+VENTAS!$E$34+VENTAS!$E$37+VENTAS!$E$40+VENTAS!$E$43+VENTAS!$E$46+VENTAS!$E$49+VENTAS!$E$52+VENTAS!$E$55+VENTAS!$E$58+VENTAS!$E$61+VENTAS!$E$64+VENTAS!$E$67+VENTAS!$E$70+VENTAS!$E$73+VENTAS!$E$76+VENTAS!$E$79+VENTAS!$E$82++VENTAS!$E$85+VENTAS!$E$88+VENTAS!$E$91+VENTAS!$E$94+VENTAS!$E$97+VENTAS!$E$100 -> 19595300
C5: TARJETA | D5: =+VENTAS!$E$11+VENTAS!$E$14+VENTAS!$E$17+VENTAS!$E$20+VENTAS!$E$23+VENTAS!$E$26+VENTAS!$E$29+VENTAS!$E$32+VENTAS!$E$35+VENTAS!$E$38+VENTAS!$E$41+VENTAS!$E$44+VENTAS!$E$47+VENTAS!$E$50+VENTAS!$E$53+VENTAS!$E$56+VENTAS!$E$59+VENTAS!$E$62+VENTAS!$E$65+VENTAS!$E$68+VENTAS!$E$71+VENTAS!$E$74+VENTAS!$E$77+VENTAS!$E$80+VENTAS!$E$83+VENTAS!$E$86+VENTAS!$E$89+VENTAS!$E$92+VENTAS!$E$95+VENTAS!$E$98+VENTAS!$E$101 -> 8103000
C6: TOTAL MES | D6: =+D4+D5 -> 27698300
C12: GASTOS Y SERVICIOS | E12: COMPRAS | F12: PERSONAL | G12: SERVICIOS | H12: OTROS GASTOS | I12: TOTAL GASTOS MES
C13: TOTALES | E13: =+'EGRESOS '!F564 -> 11554261 | F13: =+'EGRESOS '!G564 -> 5345200 | G13: =+'EGRESOS '!H564 -> 2139097 | H13: =+'EGRESOS '!I564 -> 842600 | I13: =SUM(E13:H13) -> 19881158
C14: PORCENTAJE SOBRE EL TOTAL DE LOS GASTOS | E14: =+IFERROR(E13/I13,"revisar") -> 0.5811664 | F14: =+IFERROR(F13/I13,"revisar") -> 0.26885758 | G14: =+IFERROR(G13/I13,"revisar") -> 0.10759419 | H14: =+IFERROR(H13/I13,"revisar") -> 0.042381837 | I14: =SUM(E14:H14) -> 1
C15: INGRESO AUTO
C16: PAGOS CON RETIROS
C17: TOTAL AHORROS
C21: RESUMEN MES
C22: INGRESOS | D22: =+'LIBRO DIARIO'!D39 -> 27698300
C23: GASTOS Y COSTOS | D23: =+'LIBRO DIARIO'!E39 -> 19881158 | E23: =IFERROR(D23/D22,"revisar") -> 0.71777539 | F23: PORCENTAJE DE GASTOS SOBRE LAS VENTAS
C24: GANCIA O PERDIDA OPERATIVA | D24: =+D22-D23 -> 7817142 | E24: =IFERROR(D24/D22,"revisar") -> 0.28222461 | F24: PORCENTAJE DE UTILIDAD OPERATIVA SOBRE LAS VENTAS (NO SE INCLUYE IMPUESTOS)
C26: ACCESORIOS TOTAL | D26: =+ACCESORIOS!D405 -> 94000
C27: ACCESORIOS CAJA FUERTE | D27: =+SUMIF('CAJA FUERTE'!B6:D192,'CAJA FUERTE'!B11:B12,'CAJA FUERTE'!C6:C193)-SUMIF('CAJA FUERTE'!B6:D192,'CAJA FUERTE'!B11,'CAJA FUERTE'!D6:D193) -> 0
C28: FONDO R | D28: =+SUMIF('CAJA FUERTE'!$B$6:$F$192,'RESUMEN MES'!C28,'CAJA FUERTE'!$C$6:I21)-SUMIF('CAJA FUERTE'!B6:E192,'RESUMEN MES'!C28,'CAJA FUERTE'!D6:D192) -> 0
C29: CAJA FUERTE | D29: =+'CAJA FUERTE'!F194 -> 645800
C31: GASTOS | D31: MONTO | E31: 100
C32: COLOMBINA | D32: =+SUMIF('EGRESOS '!$D$9:$F$561,'RESUMEN MES'!C32,'EGRESOS '!$F$9:$F$561) -> 1812725 | E32: =+IFERROR((D32*$E$31)/$E$13,"SIN DATOS") -> 15.688801
C33: SURTIMERCAR LA 13 | D33: =+SUMIF('EGRESOS '!$D$9:$F$561,'RESUMEN MES'!C33,'EGRESOS '!$F$9:$F$561) -> 0 | E33: =+IFERROR((D33*$E$31)/$E$13,"SIN DATOS") -> 0
C34: MAKRO | D34: =+SUMIF('EGRESOS '!$D$9:$F$561,'RESUMEN MES'!C34,'EGRESOS '!$F$9:$F$561) -> 606160 | E34: =+IFERROR((D34*$E$31)/$E$13,"SIN DATOS") -> 5.2462031
C35: CHALOS | D35: =+SUMIF('EGRESOS '!$D$9:$F$561,'RESUMEN MES'!C35,'EGRESOS '!$F$9:$F$561) -> 2146000 | E35: =+IFERROR((D35*$E$31)/$E$13,"SIN DATOS") -> 18.573235
C36: HIELO LA ROCA | D36: =+SUMIF('EGRESOS '!$D$9:$F$561,'RESUMEN MES'!C36,'EGRESOS '!$F$9:$F$561) -> 210000 | E36: =+IFERROR((D36*$E$31)/$E$13,"SIN DATOS") -> 1.8175113
C37: (OSO) DISTRIBUCIONES 2A SAS | D37: =+SUMIF('EGRESOS '!$D$9:$F$561,'RESUMEN MES'!C37,'EGRESOS '!$F$9:$F$561) -> 134400 | E37: =+IFERROR((D37*$E$31)/$E$13,"SIN DATOS") -> 1.1632072
C38: OLIMPICA | D38: =+SUMIF('EGRESOS '!$D$9:$F$561,'RESUMEN MES'!C38,'EGRESOS '!$F$9:$F$561) -> 571180 | E38: =+IFERROR((D38*$E$31)/$E$13,"SIN DATOS") -> 4.9434577
C39: ARA | D39: =+SUMIF('EGRESOS '!$D$9:$F$561,'RESUMEN MES'!C39,'EGRESOS '!$F$9:$F$561) -> 1018526 | E39: =+IFERROR((D39*$E$31)/$E$13,"SIN DATOS") -> 8.8151549
C40: ALMACENES D1 | D40: =+SUMIF('EGRESOS '!$D$9:$F$561,'RESUMEN MES'!C40,'EGRESOS '!$F$9:$F$561) -> 432070 | E40: =+IFERROR((D40*$E$31)/$E$13,"SIN DATOS") -> 3.7394862
C41: FRUTAS | D41: =+SUMIF('EGRESOS '!$D$9:$F$561,'RESUMEN MES'!C41,'EGRESOS '!$F$9:$F$561) -> 0 | E41: =+IFERROR((D41*$E$31)/$E$13,"SIN DATOS") -> 0
C42: COCA COLA | D42: =+SUMIF('EGRESOS '!$D$9:$F$561,'RESUMEN MES'!C42,'EGRESOS '!$F$9:$F$561) -> 149430 | E42: =+IFERROR((D42*$E$31)/$E$13,"SIN DATOS") -> 1.2932891
C43: RAPIMERCAR | D43: =+SUMIF('EGRESOS '!$D$9:$F$561,'RESUMEN MES'!C43,'EGRESOS '!$F$9:$F$561) -> 0 | E43: =+IFERROR((D43*$E$31)/$E$13,"SIN DATOS") -> 0
C44: BIMBO | D44: =+SUMIF('EGRESOS '!$D$9:$F$561,'RESUMEN MES'!C44,'EGRESOS '!$F$9:$F$561) -> 173874 | E44: =+IFERROR((D44*$E$31)/$E$13,"SIN DATOS") -> 1.5048474 | G44: l
C45: H2O BRISAS DE MANGLARES | D45: =+SUMIF('EGRESOS '!$D$9:$F$561,'RESUMEN MES'!C45,'EGRESOS '!$F$9:$F$561) -> 60000 | E45: =+IFERROR((D45*$E$31)/$E$13,"SIN DATOS") -> 0.51928894
C46: MERKAFRUVER RODADERO | D46: =+SUMIF('EGRESOS '!$D$9:$F$561,'RESUMEN MES'!C46,'EGRESOS '!$F$9:$F$561) -> 0 | E46: =+IFERROR((D46*$E$31)/$E$13,"SIN DATOS") -> 0
C47: MULTIMARCAS DEL CARIBE | D47: =+SUMIF('EGRESOS '!$D$9:$F$561,'RESUMEN MES'!C47,'EGRESOS '!$F$9:$F$561) -> 441687 | E47: =+IFERROR((D47*$E$31)/$E$13,"SIN DATOS") -> 3.8227196

Sheet LIBRO DIARIO
C2: SUSAN DANIELA RIVERA TORREALBA | R2: 100000
C3: C.C.1.140.418.986 | R3: 300000
C4: LIBRO DIARIO | R4: 400000
R5: 500000
E6: =+'EGRESOS '!G7 -> 0 | R6: 600000
C7: DIA | D7: VENTAS | E7: EGRESOS | F7: SALDO | R7: 700000
C8: 1 | D8: =+VENTAS!E12 -> 1162000 | E8: =+VENTAS!G12 -> 587192 | F8: =+D8-E8 -> 574808 | R8: 800000
C9: 2 | D9: =+VENTAS!E15 -> 1805000 | E9: =+VENTAS!G15 -> 821990 | F9: =+F8+D9-E9 -> 1557818 | R9: 900000
C10: 3 | D10: =+VENTAS!E18 -> 1077000 | E10: =+VENTAS!G18 -> 670470 | F10: =+F9+D10-E10 -> 1964348 | R10: 1000000
C11: 4 | D11: =+VENTAS!E21 -> 648000 | E11: =+VENTAS!G21 -> 3359657 | F11: =+F10+D11-E11 -> -747309 | R11: 1100000
C12: 5 | D12: =+VENTAS!E24 -> 422000 | E12: =+VENTAS!G24 -> 453453 | F12: =+F11+D12-E12 -> -778762 | R12: 1200000
C13: 6 | D13: =+VENTAS!E27 -> 611000 | E13: =+VENTAS!G27 -> 385678 | F13: =+F12+D13-E13 -> -553440 | R13: 1300000
C14: 7 | D14: =+VENTAS!E30 -> 660500 | E14: =+VENTAS!G30 -> 264151 | F14: =+F13+D14-E14 -> -157091 | R14: 1400000
C15: 8 | D15: =+VENTAS!E33 -> 1053000 | E15: =+VENTAS!G33 -> 673560 | F15: =+F14+D15-E15 -> 222349 | R15: 1500000
C16: 9 | D16: =+VENTAS!E36 -> 979000 | E16: =+VENTAS!G36 -> 432180 | F16: =+F15+D16-E16 -> 769169 | R16: 0
C17: 10 | D17: =+VENTAS!E39 -> 815000 | E17: =+VENTAS!G39 -> 602870 | F17: =+F16+D17-E17 -> 981299
C18: 11 | D18: =+VENTAS!E42 -> 793500 | E18: =+VENTAS!G42 -> 852713 | F18: =+F17+D18-E18 -> 922086
C19: 12 | D19: =+VENTAS!E45 -> 959500 | E19: =+VENTAS!G45 -> 511402 | F19: =+F18+D19-E19 -> 1370184
C20: 13 | D20: =+VENTAS!E48 -> 859400 | E20: =+VENTAS!G48 -> 310410 | F20: =+F19+D20-E20 -> 1919174
C21: 14 | D21: =+VENTAS!E51 -> 611000 | E21: =+VENTAS!G51 -> 876008 | F21: =+F20+D21-E21 -> 1654166
C22: 15 | D22: =+VENTAS!E54 -> 970000 | E22: =+VENTAS!G54 -> 430327 | F22: =+F21+D22-E22 -> 2193839
C23: 16 | D23: =+VENTAS!E57 -> 1212000 | E23: =+VENTAS!G57 -> 486545 | F23: =+F22+D23-E23 -> 2919294
C24: 17 | D24: =+VENTAS!E60 -> 1067000 | E24: =+VENTAS!G60 -> 748651 | F24: =+F23+D24-E24 -> 3237643
C25: 18 | D25: =+VENTAS!E63 -> 889000 | E25: =+VENTAS!G63 -> 603711 | F25: =+F24+D25-E25 -> 3522932
C26: 19 | D26: =+VENTAS!E66 -> 431500 | E26: =+VENTAS!G66 -> 340613 | F26: =+F25+D26-E26 -> 3613819
C27: 20 | D27: =+VENTAS!E69 -> 953500 | E27: =+VENTAS!G69 -> 629130 | F27: =+F26+D27-E27 -> 3938189
C28: 21 | D28: =+VENTAS!E72 -> 941200 | E28: =+VENTAS!G72 -> 569782 | F28: =+F27+D28-E28 -> 4309607
C29: 22 | D29: =+VENTAS!E75 -> 880000 | E29: =+VENTAS!G75 -> 612317 | F29: =+F28+D29-E29 -> 4577290
C30: 23 | D30: =+VENTAS!E78 -> 1139700 | E30: =+VENTAS!G78 -> 349926 | F30: =+F29+D30-E30 -> 5367064
C31: 24 | D31: =+VENTAS!E81 -> 971000 | E31: =+VENTAS!G81 -> 701988 | F31: =+F30+D31-E31 -> 5636076
C32: 25 | D32: =+VENTAS!E84 -> 851000 | E32: =+VENTAS!G84 -> 592867 | F32: =+F31+D32-E32 -> 5894209
C33: 26 | D33: =+VENTAS!E87 -> 762500 | E33: =+VENTAS!G87 -> 480775 | F33: =+F32+D33-E33 -> 6175934
C34: 27 | D34: =+VENTAS!E90 -> 1088000 | E34: =+VENTAS!G90 -> 703737 | F34: =+F33+D34-E34 -> 6560197
C35: 28 | D35: =+VENTAS!E93 -> 1249000 | E35: =+VENTAS!G93 -> 891326 | F35: =+F34+D35-E35 -> 6917871
C36: 29 | D36: =+VENTAS!E96 -> 904500 | E36: =+VENTAS!G96 -> 616829 | F36: =+F35+D36-E36 -> 7205542
C37: 30 | D37: =+VENTAS!E99 -> 932500 | E37: =+VENTAS!G99 -> 320900 | F37: =+F36+D37-E37 -> 7817142
C38: 31 | D38: =+VENTAS!E102 -> 0 | E38: =+VENTAS!G102 -> 0 | F38: =+F37+D38-E38 -> 7817142
C39: TOTAL | D39: =SUM(D8:D38) -> 27698300 | E39: =SUM(E8:E38) -> 19881158 | F39: =+F37+D38-E38 -> 7817142

Sheet ACCESORIOS
A2: DIA | B2: MODELO | C2: FORMA PAGO | D2: VENTAS $ | H2: EFECTIVO
A3: 1 | H3: NEKI
H4: DAVIPLATA
H5: TARJETA
A14: TOTAL | D14: =SUM(D3:D13) -> 0
A15: DIA | B15: MODELO | C15: FORMA PAGO | D15: VENTAS $
A16: 2
A27: TOTAL | D27: =SUM(D16:D26) -> 0
A28: DIA | B28: MODELO | C28: FORMA PAGO | D28: VENTAS $
A29: 3
A40: TOTAL | D40: =SUM(D29:D39) -> 0
A41: DIA | B41: MODELO | C41: FORMA PAGO | D41: VENTAS $
A42: 4
A53: TOTAL | D53: =SUM(D42:D52) -> 0
A54: DIA | B54: MODELO | C54: FORMA PAGO | D54: VENTAS $
A55: 5
A66: TOTAL | D66: =SUM(D55:D65) -> 0
A67: DIA | B67: MODELO | C67: FORMA PAGO | D67: VENTAS $
A68: 6
A79: TOTAL | D79: =SUM(D68:D78) -> 0
A80: DIA | B80: MODELO | C80: FORMA PAGO | D80: VENTAS $
A81: 7
A92: TOTAL | D92: =SUM(D81:D91) -> 0
A93: DIA | B93: MODELO | C93: FORMA PAGO | D93: VENTAS $
A94: 8 | B94: ARETES DE HOJA | C94: EFECTIVO | D94: 10000
B95: ANILLO PLATEADO ACERO | C95: EFECTIVO | D95: 14000
A105: TOTAL | D105: =SUM(D94:D104) -> 24000
A106: DIA | B106: MODELO | C106: FORMA PAGO | D106: VENTAS $
A107: 9 | B107: 2 ANILLOS PLATEADOS | C107: EFECTIVO | D107: 28000
A118: TOTAL | D118: =SUM(D107:D117) -> 28000
A119: DIA | B119: MODELO | C119: FORMA PAGO | D119: VENTAS $
A120: 10
A131: TOTAL | D131: =SUM(D120:D130) -> 0
A132: DIA | B132: MODELO | C132: FORMA PAGO | D132: VENTAS $
A133: 11
A144: TOTAL | D144: =SUM(D133:D143) -> 0
A145: DIA | B145: MODELO | C145: FORMA PAGO | D145: VENTAS $
A146: 12
A157: TOTAL | D157: =SUM(D146:D156) -> 0
A158: DIA | B158: MODELO | C158: FORMA PAGO | D158: VENTAS $
A159: 13
A170: TOTAL | D170: =SUM(D159:D169) -> 0
A171: DIA | B171: MODELO | C171: FORMA PAGO | D171: VENTAS $
A172: 14
A183: TOTAL | D183: =SUM(D172:D182) -> 0
A184: DIA | B184: MODELO | C184: FORMA PAGO | D184: VENTAS $
A185: 15
A196: TOTAL | D196: =SUM(D185:D195) -> 0
A197: DIA | B197: MODELO | C197: FORMA PAGO | D197: VENTAS $
A198: 16
A209: TOTAL | D209: =SUM(D198:D208) -> 0
A210: DIA | B210: MODELO | C210: FORMA PAGO | D210: VENTAS $
A211: 17 | B211: anillo princesa corona | C211: EFECTIVO | D211: 14000
A222: TOTAL | D222: =SUM(D211:D221) -> 14000
A223: DIA | B223: MODELO | C223: FORMA PAGO | D223: VENTAS $
A224: 18
A235: TOTAL | D235: =SUM(D224:D234) -> 0
A236: DIA | B236: MODELO | C236: FORMA PAGO | D236: VENTAS $
A237: 19
A248: TOTAL | D248: =SUM(D237:D247) -> 0
A249: DIA | B249: MODELO | C249: FORMA PAGO | D249: VENTAS $
A250: 20 | B250: JUEGO MARIPOSA | C250: TARJETA | D250: 20000
A261: TOTAL | D261: =SUM(D250:D260) -> 20000
A262: DIA | B262: MODELO | C262: FORMA PAGO | D262: VENTAS $
A263: 21
A274: TOTAL | D274: =SUM(D263:D273) -> 0
A275: DIA | B275: MODELO | C275: FORMA PAGO | D275: VENTAS $
A276: 22
A287: TOTAL | D287: =SUM(D276:D286) -> 0
A288: DIA | B288: MODELO | C288: FORMA PAGO | D288: VENTAS $
A289: 23
A300: TOTAL | D300: =SUM(D289:D299) -> 0
A301: DIA | B301: MODELO | C301: FORMA PAGO | D301: VENTAS $
A302: 24
A313: TOTAL | D313: =SUM(D302:D312) -> 0
A314: DIA | B314: MODELO | C314: FORMA PAGO | D314: VENTAS $
A315: 25
A326: TOTAL | D326: =SUM(D315:D325) -> 0
A327: DIA | B327: MODELO | C327: FORMA PAGO | D327: VENTAS $
A328: 26 | B328: anillo pareja de niños | C328: EFECTIVO | D328: 8000
A339: TOTAL | D339: =SUM(D328:D338) -> 8000
A340: DIA | B340: MODELO | C340: FORMA PAGO | D340: VENTAS $
A341: 27
A352: TOTAL | D352: =SUM(D341:D351) -> 0
A353: DIA | B353: MODELO | C353: FORMA PAGO | D353: VENTAS $
A354: 28
A365: TOTAL | D365: =SUM(D354:D364) -> 0
A366: DIA | B366: MODELO | C366: FORMA PAGO | D366: VENTAS $
A367: 29
A378: TOTAL | D378: =SUM(D367:D377) -> 0
A379: DIA | B379: MODELO | C379: FORMA PAGO | D379: VENTAS
A380: 30
A391: TOTAL | D391: =SUM(D380:D390) -> 0
A392: DIA | B392: MODELO | C392: FORMA PAGO | D392: VENTAS $
A393: 31
A404: TOTAL | D404: =SUM(D393:D403) -> 0
A405: TOTAL | D405: =+D14+D27+D40+D53+D66+D79+D92+D105+D118+D131+D144+D157+D170+D183+D196+D209+D222+D235+D248+D261+D274+D287+D300+D313+D326+D339+D352+D365+D378+D391+D404 -> 94000
C408: EFECTIVO | D408: =+SUMIF($C$3:$D$403,C408,$D$3:$I$407) -> 74000
C409: NEKI | D409: =+SUMIF($C$3:$D$403,C409,$D$3:$I$407) -> 0
C410: DAVIPLATA | D410: =+SUMIF($C$3:$D$403,C410,$D$3:$I$407) -> 0
...

Sheet CAJA FUERTE
I2: DIA | J2: BASE INICIAL | K2: VENTA EFEC | L2: VENTA TARJETA | M2: EGRESOS | N2: BASE FINAL | O2: CF
O3: =F6 -> 392550
I4: 1 | J4: 1300000 | K4: =VENTAS!E10 -> 824000 | N4: 1300000 | O4: =O3+K4-M4-N4 -> -83450
A5: DIA | C5: DEPOSITO | D5: RETIRO AUT. | E5: BANCO | F5: SALDO | I5: 2 | J5: 1300000 | K5: =VENTAS!E13 -> 1219000 | N5: 1300000 | O5: =+J5+K5-M5-N5 -> 1219000
A6: 1 | B6: SALDO MES ANTERIOR | C6: 392550 | D6: 0 | F6: =+C6 -> 392550 | I6: 3 | J6: 1300001 | K6: =VENTAS!E14 -> 586000 | N6: 1300001 | O6: =+J6+K6-M6-N6 -> 586000
B7: DEPOSITO CR | C7: 441000 | D7: 0 | E7: 0 | F7: =+C7-D7-E7+F6 -> 833550 | I7: 4 | J7: 1300002 | K7: =VENTAS!E15 -> 1805000 | N7: 1300002 | O7: =+J7+K7-M7-N7 -> 1805000
B8: DEPOSITO CR | C8: 383000 | D8: 0 | E8: 0 | F8: =+C8-D8-E8+F7 -> 1216550 | I8: 5 | J8: 1300003 | K8: =VENTAS!E16 -> 767000 | N8: 1300003 | O8: =+J8+K8-M8-N8 -> 767000
B9: RT REPOSICION | C9: 0 | D9: 477150 | E9: 0 | F9: =+C9-D9-E9+F8 -> 739400 | I9: 6 | J9: 1300004 | K9: =VENTAS!E17 -> 310000 | N9: 1300004 | O9: =+J9+K9-M9-N9 -> 310000
C10: 0 | D10: =110000 -> 110000 | E10: 0 | F10: =+C10-D10-E10+F9 -> 629400 | I10: 7 | J10: 1300005 | K10: =VENTAS!E18 -> 1077000 | N10: 1300005 | O10: =+J10+K10-M10-N10 -> 1077000
B11: ACCESORIOS | C11: =+SUMIF(ACCESORIOS!C3:D13,ACCESORIOS!H2,ACCESORIOS!D3:D13) -> 0 | D11: 0 | E11: 0 | F11: =+C11-D11-E11+F10 -> 629400 | I11: 8 | J11: 1300011 | K11: =VENTAS!E24 -> 422000 | N11: 1300011 | O11: =+J11+K11-M11-N11 -> 422000
A12: TOTAL | C12: =SUM(C6:C11) -> 1216550 | D12: =SUM(D6:D11) -> 587150 | E12: =SUM(E6:E11) -> 0 | F12: =F11 -> 629400 | I12: 9 | J12: 1300012 | K12: =VENTAS!E25 -> 413000 | N12: 1300012 | O12: =+J12+K12-M12-N12 -> 413000
A13: 2 | B13: DEPOSITO CR | C13: 311000 | D13: 0 | E13: 0 | F13: =+C13-D13-E13+F12 -> 940400 | I13: 10 | J13: 1300013 | K13: =VENTAS!E26 -> 198000 | N13: 1300013 | O13: =+J13+K13-M13-N13 -> 198000
B14: DEPOSITO CR | C14: 908000 | D14: 0 | E14: 0 | F14: =+C14-D14-E14+F13 -> 1848400 | I14: 11 | J14: 1300014 | K14: =VENTAS!E27 -> 611000 | N14: 1300014
B15: RT REPOSICION | C15: 0 | D15: 822000 | E15: 0 | F15: =+C15-D15-E15+F14 -> 1026400 | I15: 12 | J15: 1300015 | K15: =VENTAS!E28 -> 505500 | N15: 1300015 | O15: =+J15+K15-M15-N15 -> 505500
B16: RETIRO AUTORIZADO SUSAN RIVERA | C16: 0 | D16: 700000 | E16: 0 | F16: =+C16-D16-E16+F15 -> 326400 | I16: 13 | J16: 1300016 | K16: =VENTAS!E29 -> 155000 | N16: 1300016
B17: ACCESORIOS | C17: =+SUMIF(ACCESORIOS!C16:D26,ACCESORIOS!H2,ACCESORIOS!D16:D26) -> 0 | D17: 0 | E17: 0 | F17: =+C17-D17-E17+F16 -> 326400 | I17: 14 | J17: 1300017 | K17: =VENTAS!E30 -> 660500 | N17: 1300017 | O17: =+J17+K17-M17-N17 -> 660500 | AD17: Arriendo
A18: TOTAL | C18: =SUM(C13:C17) -> 1219000 | D18: =SUM(D13:D17) -> 1522000 | E18: =SUM(E13:E17) -> 0 | F18: =F17 -> 326400 | I18: 15 | J18: 1300018 | K18: =VENTAS!E31 -> 800000 | N18: 1300018 | O18: =+J18+K18-M18-N18 -> 800000 | AD18: Deposito 24079920959
A19: 3 | B19: DEPOSITO CR | C19: 363000 | D19: 0 | E19: 0 | F19: =+C19-D19-E19+F18 -> 689400 | I19: 16 | J19: 1300019 | K19: =VENTAS!E32 -> 253000 | N19: 1300019 | O19: =+J19+K19-M19-N19 -> 253000 | AD19: Servicio luz
B20: DEPOSITO CR | C20: 404000 | D20: 0 | E20: 0 | F20: =+C20-D20-E20+F19 -> 1093400 | I20: 17 | J20: 1300020 | K20: =VENTAS!E33 -> 1053000 | N20: 1300020 | AD20: Servicio agua
B21: RT REPOSICION | C21: 0 | D21: 650600 | E21: 0 | F21: =+C21-D21-E21+F20 -> 442800 | I21: 18 | J21: 1300021 | K21: =VENTAS!E34 -> 770000 | N21: 1300021
C22: 0 | D22: 0 | E22: 0 | F22: =+C22-D22-E22+F21 -> 442800 | I22: 19 | J22: 1300022 | K22: =VENTAS!E35 -> 209000 | N22: 1300022 | O22: =+J22+K22-M22-N22 -> 209000 | AD22: Servicio gas
B23: ACCESORIOS | C23: =+SUMIF(ACCESORIOS!C29:D39,ACCESORIOS!H2,ACCESORIOS!D29:D39) -> 0 | D23: 0 | E23: 0 | F23: =+C23-D23-E23+F22 -> 442800 | I23: 20 | J23: 1300023 | K23: =VENTAS!E36 -> 979000 | N23: 1300023 | O23: =+J23+K23-M23-N23 -> 979000 | AD23: Deposito 24070185038
A24: TOTAL | C24: =SUM(C19:C23) -> 767000 | D24: =SUM(D19:D23) -> 650600 | E24: =SUM(E19:E23) -> 0 | F24: =F23 -> 442800 | I24: 21 | J24: 1300024 | K24: =VENTAS!E37 -> 591000 | N24: 1300024 | O24: =+J24+K24-M24-N24 -> 591000 | AD24: RETIRO AUTORIZADO SUSAN RIVERA
A25: 4 | B25: DEPOSITO CR | C25: 161000 | D25: 0 | E25: 0 | F25: =+C25-D25-E25+F24 -> 603800 | I25: 22 | J25: 1300025 | K25: =VENTAS!E38 -> 224000 | N25: 1300025 | O25: =+J25+K25-M25-N25 -> 224000 | AD25: RETIRO AUTORIZADO JUAN VILLABONA
B26: DEPOSITO CR | C26: 288000 | D26: 0 | E26: 0 | F26: =+C26-D26-E26+F25 -> 891800 | I26: 23 | J26: 1300026 | K26: =VENTAS!E39 -> 815000 | N26: 1300026 | AD26: SALDO MES ANTERIOR
B27: RT REPOSICION | C27: 0 | D27: 285750 | E27: 0 | F27: =+C27-D27-E27+F26 -> 606050 | I27: 24 | J27: 1300027 | K27: =VENTAS!E40 -> 610500 | N27: 1300027
B28: RETIRO AUTORIZADO JUAN VILLABONA | C28: 0 | D28: =406000+105000 -> 511000 | E28: 0 | F28: =+C28-D28-E28+F27 -> 95050 | I28: 25 | J28: 1300028 | K28: =VENTAS!E41 -> 183000 | N28: 1300028 | O28: =+J28+K28-M28-N28 -> 183000 | AD28: DEPOSITO CR
B29: ACCESORIOS | C29: =+SUMIF(ACCESORIOS!C42:D52,ACCESORIOS!H2,ACCESORIOS!D42:D52) -> 0 | D29: 0 | E29: 0 | F29: =+C29-D29-E29+F28 -> 95050 | I29: 26 | J29: 1300000 | K29: =VENTAS!E82 -> 626000 | N29: 1300000 | O29: =+J29+K29-M29-N29 -> 626000 | AD29: RT REPOSICION
A30: TOTAL | C30: =SUM(C25:C29) -> 449000 | D30: =SUM(D25:D29) -> 796750 | E30: =SUM(E25:E29) -> 0 | F30: =F29 -> 95050 | I30: 27 | J30: 1300001 | K30: =VENTAS!E83 -> 225000 | N30: 1300001 | O30: =+J30+K30-M30-N30 -> 225000 | AD30: FONDO R
A31: 5 | B31: DEPOSITO CR | C31: =35000+5000 -> 40000 | D31: 0 | E31: 0 | F31: =+C31-D31-E31+F30 -> 135050 | I31: 28 | J31: 1300002 | K31: =VENTAS!E84 -> 851000 | N31: 1300002 | O31: =+J31+K31-M31-N31 -> 851000 | AD31: ACCESORIOS
B32: DEPOSITO CR | C32: 253000 | D32: 0 | E32: 0 | F32: =+C32-D32-E32+F31 -> 388050 | I32: 29 | J32: 1300003 | K32: =VENTAS!E85 -> 404500 | N32: 1300003
B33: RT REPOSICION | C33: 0 | D33: 169800 | E33: 0 | F33: =+C33-D33-E33+F32 -> 218250 | I33: 30 | J33: 1300004 | K33: =VENTAS!E86 -> 358000 | N33: 1300004
C34: 0 | D34: 212650 | E34: 0 | F34: =+C34-D34-E34+F33 -> 5600 | I34: 31 | J34: 1300005 | K34: =VENTAS!E87 -> 762500 | N34: 1300005 | O34: =+J34+K34-M34-N34 -> 762500 | AD34: FALTANTE APROBADO
B35: ACCESORIOS | C35: =+SUMIF(ACCESORIOS!C55:D65,ACCESORIOS!H2,ACCESORIOS!D55:D65) -> 0 | D35: 0 | E35: 0 | F35: =+C35-D35-E35+F34 -> 5600 | O35: =+J35+K35-M35-N35 -> 0 | AD35: SOBRANTE APROBADO
A36: TOTAL | C36: =SUM(C31:C35) -> 293000 | D36: =SUM(D31:D35) -> 382450 | E36: =SUM(E31:E35) -> 0 | F36: =F35 -> 5600 | O36: =+J36+K36-M36-N36 -> 0
A37: 6 | B37: DEPOSITO CR | C37: 168000 | D37: 0 | E37: 0 | F37: =+C37-D37-E37+F36 -> 173600 | O37: =+J37+K37-M37-N37 -> 0
B38: DEPOSITO CR | C38: 245000 | D38: 0 | E38: 0 | F38: =+C38-D38-E38+F37 -> 418600
B39: RT REPOSICION | C39: 0 | D39: 231400 | E39: 0 | F39: =+C39-D39-E39+F38 -> 187200
C40: 0 | D40: 187200 | E40: 0 | F40: =+C40-D40-E40+F39 -> 0
B41: ACCESORIOS | C41: =+SUMIF(ACCESORIOS!C68:D78,ACCESORIOS!H2,ACCESORIOS!D68:D78) -> 0 | D41: 0 | E41: 0 | F41: =+C41-D41-E41+F40 -> 0
A42: TOTAL | C42: =SUM(C37:C41) -> 413000 | D42: =SUM(D37:D41) -> 418600 | E42: =SUM(E37:E41) -> 0 | F42: =F41 -> 0
A43: 7 | B43: DEPOSITO CR | C43: 142500 | D43: 0 | E43: 0 | F43: =+C43-D43-E43+F42 -> 142500
B44: DEPOSITO CR | C44: 363000 | D44: 0 | E44: 0 | F44: =+C44-D44-E44+F43 -> 505500
B45: RT REPOSICION | C45: 0 | D45: 505500 | E45: 0 | F45: =+C45-D45-E45+F44 -> 0
C46: 0 | D46: 0 | E46: 0 | F46: =+C46-D46-E46+F45 -> 0
B47: ACCESORIOS | C47: =+SUMIF(ACCESORIOS!C81:D91,ACCESORIOS!H2,ACCESORIOS!D81:D91) -> 0 | D47: 0 | E47: 0 | F47: =+C47-D47-E47+F46 -> 0
A48: TOTAL | C48: =SUM(C43:C47) -> 505500 | D48: =SUM(D43:D47) -> 505500 | E48: =SUM(E43:E47) -> 0 | F48: =F47 -> 0
A49: 8 | B49: DEPOSITO CR | C49: 252000 | D49: 0 | E49: 0 | F49: =+C49-D49-E49+F48 -> 252000
B50: DEPOSITO CR | C50: 548000 | E50: 0 | F50: =+C50-D50-E50+F49 -> 800000
B51: RT REPOSICION | C51: 0 | D51: 673600 | E51: 0 | F51: =+C51-D51-E51+F50 -> 126400
C52: 28500 | D52: 0 | E52: 0 | F52: =+C52-D52-E52+F51 -> 154900
B53: ACCESORIOS | C53: =+SUMIF(ACCESORIOS!C94:D104,ACCESORIOS!H2,ACCESORIOS!D94:D104) -> 24000 | D53: 0 | E53: 0 | F53: =+C53-D53-E53+F52 -> 178900
A54: TOTAL | C54: =SUM(C49:C53) -> 852500 | D54: =SUM(D49:D53) -> 673600 | E54: =SUM(E49:E53) -> 0 | F54: =F53 -> 178900
A55: 9 | B55: DEPOSITO CR | C55: 214000 | D55: 0 | E55: 0 | F55: =+C55-D55-E55+F54 -> 392900
B56: DEPOSITO CR | C56: 556000 | D56: 0 | E56: 0 | F56: =+C56-D56-E56+F55 -> 948900
B57: RT REPOSICION | C57: 0 | D57: 532200 | E57: 0 | F57: =+C57-D57-E57+F56 -> 416700
C58: 100 | D58: 0 | E58: 0 | F58: =+C58-D58-E58+F57 -> 416800
B59: ACCESORIOS | C59: =+SUMIF(ACCESORIOS!C107:D117,ACCESORIOS!H2,ACCESORIOS!D107:D117) -> 28000 | D59: 0 | E59: 0 | F59: =+C59-D59-E59+F58 -> 444800
A60: TOTAL | C60: =SUM(C55:C59) -> 798100 | D60: =SUM(D55:D59) -> 532200 | E60: =SUM(E55:E59) -> 0 | F60: =F59 -> 444800
A61: 10 | B61: DEPOSITO CR | C61: 173000 | D61: 0 | E61: 0 | F61: =+C61-D61-E61+F60 -> 617800
B62: DEPOSITO CR | C62: 418000 | D62: 0 | E62: 0 | F62: =+C62-D62-E62+F61 -> 1035800
B63: RT REPOSICION | C63: 0 | D63: 492900 | E63: 0 | F63: =+C63-D63-E63+F62 -> 542900
B64: RETIRO AUTORIZADO JUAN VILLABONA | D64: 110000 | E64: 0 | F64: =+C64-D64-E64+F63 -> 432900
B65: ANA DEUDA BILLETE | C65: 77100 | F65: =+C65-D65-E65+F64 -> 510000
B66: ACCESORIOS | C66: =+SUMIF(ACCESORIOS!C120:D130,ACCESORIOS!H2,ACCESORIOS!D120:D130) -> 0 | D66: 0 | E66: 0 | F66: =+C66-D66-E66+F65 -> 510000
A67: TOTAL | C67: =SUM(C61:C66) -> 668100 | D67: =SUM(D61:D66) -> 602900 | E67: =SUM(E61:E66) -> 0 | F67: =F66 -> 510000
A68: 11 | B68: DEPOSITO CR | C68: 213500 | D68: 0 | E68: 0 | F68: =+C68-D68-E68+F67 -> 723500
B69: DEPOSITO CR | C69: 397000 | D69: 0 | E69: 0 | F69: =+C69-D69-E69+F68 -> 1120500
B70: RT REPOSICION | C70: 0 | D70: 559200 | E70: 0 | F70: =+C70-D70-E70+F69 -> 561300
C71: 0 | D71: 293600 | E71: 0 | F71: =+C71-D71-E71+F70 -> 267700
B72: ACCESORIOS | C72: =+SUMIF(ACCESORIOS!C133:D143,ACCESORIOS!H2,ACCESORIOS!D133:D143) -> 0 | D72: 0 | E72: 0 | F72: =+C72-D72-E72+F71 -> 267700
A73: TOTAL | C73: =SUM(C68:C72) -> 610500 | D73: =SUM(D68:D72) -> 852800 | E73: =SUM(E68:E72) -> 0 | F73: =F72 -> 267700
A74: 12 | B74: DEPOSITO CR | C74: 231000 | D74: 0 | E74: 0 | F74: =+C74-D74-E74+F73 -> 498700
B75: DEPOSITO CR | C75: 405000 | D75: 0 | E75: 0 | F75: =+C75-D75-E75+F74 -> 903700
B76: RT REPOSICION | C76: 0 | D76: 511500 | E76: 0 | F76: =+C76-D76-E76+F75 -> 392200
C77: 0 | D77: 0 | E77: 0 | F77: =+C77-D77-E77+F76 -> 392200
B78: ACCESORIOS | C78: =+SUMIF(ACCESORIOS!C146:D156,ACCESORIOS!H2,ACCESORIOS!D146:D156) -> 0 | D78: 0 | E78: 0 | F78: =+C78-D78-E78+F77 -> 392200
A79: TOTAL | C79: =SUM(C74:C78) -> 636000 | D79: =SUM(D74:D78) -> 511500 | E79: =SUM(E74:E78) -> 0 | F79: =F78 -> 392200
A80: 13 | B80: DEPOSITO CR | C80: 237000 | D80: 0 | E80: 0 | F80: =+C80-D80-E80+F79 -> 629200
B81: DEPOSITO CR | C81: 414400 | D81: 0 | E81: 0 | F81: =+C81-D81-E81+F80 -> 1043600
B82: RT REPOSICION | C82: 0 | D82: 310400 | E82: 0 | F82: =+C82-D82-E82+F81 -> 733200
C83: 0 | D83: 0 | E83: 0 | F83: =+C83-D83-E83+F82 -> 733200
B84: ACCESORIOS | C84: =+SUMIF(ACCESORIOS!C159:D169,ACCESORIOS!H2,ACCESORIOS!D159:D169) -> 0 | D84: 0 | E84: 0 | F84: =+C84-D84-E84+F83 -> 733200
A85: TOTAL | C85: =SUM(C80:C84) -> 651400 | D85: =SUM(D80:D84) -> 310400 | E85: =SUM(E80:E84) -> 0 | F85: =F84 -> 733200
A86: 14 | B86: DEPOSITO CR | C86: 152000 | D86: 0 | E86: 0 | F86: =+C86-D86-E86+F85 -> 885200
B87: DEPOSITO CR | C87: 157000 | D87: 0 | E87: 0 | F87: =+C87-D87-E87+F86 -> 1042200
B88: RT REPOSICION | C88: 0 | D88: 582800 | E88: 0 | F88: =+C88-D88-E88+F87 -> 459400
C89: 0 | D89: 289200 | E89: 0 | F89: =+C89-D89-E89+F88 -> 170200
B90: ACCESORIOS | C90: =+SUMIF(ACCESORIOS!C172:D182,ACCESORIOS!H2,ACCESORIOS!D172:D182) -> 0 | D90: 0 | E90: 0 | F90: =+C90-D90-E90+F89 -> 170200
A91: TOTAL | C91: =SUM(C86:C90) -> 309000 | D91: =SUM(D86:D90) -> 872000 | E91: =SUM(E86:E90) -> 0 | F91: =F90 -> 170200
A92: 15 | B92: DEPOSITO CR | C92: 236000 | D92: 0 | E92: 0 | F92: =+C92-D92-E92+F91 -> 406200
B93: DEPOSITO CR | C93: 561000 | D93: 0 | E93: 0 | F93: =+C93-D93-E93+F92 -> 967200
B94: RT REPOSICION | C94: 0 | D94: 430300 | E94: 0 | F94: =+C94-D94-E94+F93 -> 536900
C95: 0 | D95: 0 | E95: 0 | F95: =+C95-D95-E95+F94 -> 536900
B96: ACCESORIOS | C96: =+SUMIF(ACCESORIOS!C185:D195,ACCESORIOS!H2,ACCESORIOS!D185:D195) -> 0 | D96: 0 | E96: 0 | F96: =+C96-D96-E96+F95 -> 536900
A97: TOTAL | C97: =SUM(C92:C96) -> 797000 | D97: =SUM(D92:D96) -> 430300 | E97: =SUM(E92:E96) -> 0 | F97: =F96 -> 536900
A98: 16 | B98: DEPOSITO CR | C98: 59000 | D98: 0 | E98: 0 | F98: =+C98-D98-E98+F97 -> 595900
B99: DEPOSITO CR | C99: 820000 | D99: 0 | E99: 0 | F99: =+C99-D99-E99+F98 -> 1415900
B100: RT REPOSICION | C100: 0 | D100: 486600 | E100: 0 | F100: =+C100-D100-E100+F99 -> 929300
C101: 0 | D101: 0 | E101: 0 | F101: =+C101-D101-E101+F100 -> 929300
...

Sheet RESUMEN GASTOS
A2: SUSAN DANIELA RIVERA TORREALBA
A3: C.C.1.140.418.986
A4: RESUMEN GASTOS
A5: MES DE FEBRERO 2022
A7: TERCERO | B7: DESCRIPCION | C7: COSTO | D7: GASTO | E7: TOTAL
A53: TOTALES | C53: =SUM(C8:C52) -> 0 | D53: =SUM(D8:D52) -> 0 | E53: =SUM(E8:E52) -> 0
